geokoord/__init__.py
geokoord/enums.py
geokoord/koordinates/__init__.py
geokoord/koordinates/exports.py
geokoord-0.2.1.dist-info/METADATA
geokoord-0.2.1.dist-info/WHEEL
geokoord-0.2.1.dist-info/licenses/LICENSE
geokoord-0.2.1.dist-info/RECORD
